.travis.yml
AUTHORS.rst
ChangeLog.rst
LICENSE.rst
MANIFEST.in
README.rst
appinfo.py
build.cmd
requirements-dev.txt
requirements.txt
setup.py
setup_py2exe.py
setup_utils.py
shippable.yml
tox.ini
doc/authors.rst
doc/changelog.rst
doc/conf.py
doc/index.rst
doc/license.rst
doc/readme.rst
doc/reference.rst
pythonhosted.org/doc.zip
pythonhosted.org/index.html
pythonhosted.org/redir2RTD.zip
raspi/AUTHORS.txt
raspi/ChangeLog.txt
raspi/LICENSE.txt
raspi/README.txt
raspi/__init__.py
raspi/appinfo.py
raspi/raspi.py
raspi.egg-info/PKG-INFO
raspi.egg-info/SOURCES.txt
raspi.egg-info/dependency_links.txt
raspi.egg-info/entry_points.txt
raspi.egg-info/requires.txt
raspi.egg-info/top_level.txt
raspi/doc/.buildinfo
raspi/doc/authors.html
raspi/doc/changelog.html
raspi/doc/genindex.html
raspi/doc/index.html
raspi/doc/license.html
raspi/doc/objects.inv
raspi/doc/raspi.pdf
raspi/doc/readme.html
raspi/doc/reference.html
raspi/doc/search.html
raspi/doc/searchindex.js
raspi/doc/_sources/authors.txt
raspi/doc/_sources/changelog.txt
raspi/doc/_sources/index.txt
raspi/doc/_sources/license.txt
raspi/doc/_sources/readme.txt
raspi/doc/_sources/reference.txt
raspi/doc/_static/ajax-loader.gif
raspi/doc/_static/alabaster.css
raspi/doc/_static/basic.css
raspi/doc/_static/comment-bright.png
raspi/doc/_static/comment-close.png
raspi/doc/_static/comment.png
raspi/doc/_static/doctools.js
raspi/doc/_static/down-pressed.png
raspi/doc/_static/down.png
raspi/doc/_static/file.png
raspi/doc/_static/jquery-1.11.1.js
raspi/doc/_static/jquery.js
raspi/doc/_static/minus.png
raspi/doc/_static/plus.png
raspi/doc/_static/pygments.css
raspi/doc/_static/searchtools.js
raspi/doc/_static/underscore-1.3.1.js
raspi/doc/_static/underscore.js
raspi/doc/_static/up-pressed.png
raspi/doc/_static/up.png
raspi/doc/_static/websupport.js