Metadata-Version: 1.1
Name: raspi
Version: 0.0.2
Summary: This module provides some helper functions to use with the Raspberry Pi and the RPi.GPIO.
Home-page: https://github.com/jcrmatos/raspi
Author: Joao Carlos Roseta Matos
Author-email: jcrmatos@gmail.com
License: GNU General Public License v2 or later (GPLv2+)
Keywords: r,a,s,p,b,e,r,r,y, ,p,i, ,g,p,i,o
Platform: UNKNOWN
Classifier: Development Status :: 4 - Beta
Classifier: Environment :: Console
Classifier: Intended Audience :: Developers
Classifier: Intended Audience :: End Users/Desktop
Classifier: License :: OSI Approved :: GNU General Public License v2 or later (GPLv2+)
Classifier: Natural Language :: English
Classifier: Operating System :: OS Independent
Classifier: Programming Language :: Python
Classifier: Programming Language :: Python :: 2
Classifier: Programming Language :: Python :: 2.7
Classifier: Programming Language :: Python :: 3
Classifier: Programming Language :: Python :: 3.4
Classifier: Topic :: Software Development :: Libraries :: Python Modules
